eppy-stubs/__init__.pyi
eppy-stubs/eppy/modeleditor.pyi
eppy-stubs/py.typed
eppy_stubs-0.1.3.dist-info/WHEEL
eppy_stubs-0.1.3.dist-info/METADATA
eppy_stubs-0.1.3.dist-info/RECORD
